{
  "metadata": {
    "backup_date": "2026-03-02",
    "source_files": [
      "lib/add_device.dart",
      "lib/dashboard.dart"
    ],
    "total_locations": 41,
    "purpose": "Backup koordinat sebelum migration ke PNG layout-based map"
  },
  "reference_center": {
    "name": "Terminal Nilam",
    "latitude": -7.207277,
    "longitude": 112.723613,
    "default_zoom": 16.5
  },
  "bounding_box": {
    "current": {
      "lat_min": -7.210500,
      "lat_max": -7.204000,
      "lng_min": 112.721800,
      "lng_max": 112.725500
    },
    "recommended_with_margin": {
      "lat_min": -7.210500,
      "lat_max": -7.203500,
      "lng_min": 112.721500,
      "lng_max": 112.725800
    }
  },
  "container_yards": [
    {
      "id": "CY1",
      "name": "Container Yard 1",
      "latitude": -7.205843,
      "longitude": 112.723164,
      "color": "#FFB74D"
    },
    {
      "id": "CY2",
      "name": "Container Yard 2",
      "latitude": -7.209152,
      "longitude": 112.724487,
      "color": "#66BB6A"
    },
    {
      "id": "CY3",
      "name": "Container Yard 3",
      "latitude": -7.208712,
      "longitude": 112.723270,
      "color": "#EF9A9A"
    }
  ],
  "towers": [
    {
      "number": 1,
      "name": "Tower 1",
      "label": "1",
      "latitude": -7.209459,
      "longitude": 112.724717,
      "container_yard": "CY2"
    },
    {
      "number": 2,
      "name": "Tower 2",
      "label": "2",
      "latitude": -7.209191,
      "longitude": 112.725250,
      "container_yard": "CY2"
    },
    {
      "number": 3,
      "name": "Tower 3",
      "label": "3",
      "latitude": -7.208561,
      "longitude": 112.724946,
      "container_yard": "CY2"
    },
    {
      "number": 4,
      "name": "Tower 4",
      "label": "4",
      "latitude": -7.208150,
      "longitude": 112.724395,
      "container_yard": "CY2"
    },
    {
      "number": 5,
      "name": "Tower 5",
      "label": "5",
      "latitude": -7.208262,
      "longitude": 112.724161,
      "container_yard": "CY2"
    },
    {
      "number": 6,
      "name": "Tower 6",
      "label": "6",
      "latitude": -7.208956,
      "longitude": 112.724173,
      "container_yard": "CY2"
    },
    {
      "number": 7,
      "name": "Tower 7",
      "label": "7",
      "latitude": -7.207690,
      "longitude": 112.723693,
      "container_yard": "CY1"
    },
    {
      "number": 8,
      "name": "Tower 8",
      "label": "8",
      "latitude": -7.207567,
      "longitude": 112.723945,
      "container_yard": "CY1"
    },
    {
      "number": 9,
      "name": "Tower 9",
      "label": "9",
      "latitude": -7.207156,
      "longitude": 112.724302,
      "container_yard": "CY1"
    },
    {
      "number": 10,
      "name": "Tower 10",
      "label": "10",
      "latitude": -7.204341,
      "longitude": 112.722956,
      "container_yard": "CY1"
    },
    {
      "number": 11,
      "name": "Tower 11",
      "label": "11",
      "latitude": -7.204080,
      "longitude": 112.722354,
      "container_yard": "CY1"
    },
    {
      "number": 27,
      "name": "Tower 12A",
      "label": "12A",
      "latitude": -7.204228,
      "longitude": 112.722045,
      "container_yard": "CY1",
      "tower_id_hint": "12A"
    },
    {
      "number": 12,
      "name": "Tower 12",
      "label": "12",
      "latitude": -7.204460,
      "longitude": 112.721970,
      "container_yard": "CY1"
    },
    {
      "number": 13,
      "name": "Tower 13",
      "label": "13",
      "latitude": -7.205410,
      "longitude": 112.722386,
      "container_yard": "CY1"
    },
    {
      "number": 14,
      "name": "Tower 14",
      "label": "14",
      "latitude": -7.206786,
      "longitude": 112.723023,
      "container_yard": "CY1"
    },
    {
      "number": 15,
      "name": "Tower 15",
      "label": "15",
      "latitude": -7.207566,
      "longitude": 112.723469,
      "container_yard": "CY1"
    },
    {
      "number": 16,
      "name": "Tower 16",
      "label": "16",
      "latitude": -7.207342,
      "longitude": 112.723059,
      "container_yard": "CY1"
    },
    {
      "number": 17,
      "name": "Tower 17",
      "label": "17",
      "latitude": -7.209240,
      "longitude": 112.723915,
      "container_yard": "CY1"
    },
    {
      "number": 18,
      "name": "Tower 18",
      "label": "18",
      "latitude": -7.210090,
      "longitude": 112.724321,
      "container_yard": "CY3"
    },
    {
      "number": 19,
      "name": "Tower 19",
      "label": "19",
      "latitude": -7.210336,
      "longitude": 112.723639,
      "container_yard": "CY3"
    },
    {
      "number": 20,
      "name": "Tower 20",
      "label": "20",
      "latitude": -7.210082,
      "longitude": 112.723303,
      "container_yard": "CY3"
    },
    {
      "number": 21,
      "name": "Tower 21",
      "label": "21",
      "latitude": -7.209070,
      "longitude": 112.722914,
      "container_yard": "CY3"
    },
    {
      "number": 22,
      "name": "Tower 22",
      "label": "22",
      "latitude": -7.208501,
      "longitude": 112.722942,
      "container_yard": "CY3"
    },
    {
      "number": 23,
      "name": "Tower 23",
      "label": "23",
      "latitude": -7.208017,
      "longitude": 112.722195,
      "container_yard": "CY3"
    },
    {
      "number": 24,
      "name": "Tower 24",
      "label": "24",
      "latitude": -7.207314,
      "longitude": 112.722005,
      "container_yard": "CY3"
    },
    {
      "number": 25,
      "name": "Tower 25",
      "label": "25",
      "latitude": -7.207213,
      "longitude": 112.722232,
      "container_yard": "CY3"
    },
    {
      "number": 26,
      "name": "Tower 26",
      "label": "26",
      "latitude": -7.207029,
      "longitude": 112.722613,
      "container_yard": "CY3"
    }
  ],
  "devices": {
    "cctv": [
      {
        "id": "CC01",
        "name": "CC01 - CY1",
        "latitude": -7.204768,
        "longitude": 112.723299,
        "container_yard": "CY1"
      },
      {
        "id": "CC02",
        "name": "CC02 - CY1",
        "latitude": -7.205358,
        "longitude": 112.723571,
        "container_yard": "CY1"
      },
      {
        "id": "CC03",
        "name": "CC03 - CY1",
        "latitude": -7.205947,
        "longitude": 112.723840,
        "container_yard": "CY1"
      },
      {
        "id": "CC04",
        "name": "CC04 - CY1",
        "latitude": -7.206656,
        "longitude": 112.724164,
        "container_yard": "CY1"
      }
    ],
    "rtg": [
      {
        "id": "RTG01",
        "name": "RTG01 - CY1",
        "latitude": -7.204805,
        "longitude": 112.722550,
        "container_yard": "CY1"
      },
      {
        "id": "RTG02",
        "name": "RTG02 - CY1",
        "latitude": -7.205129,
        "longitude": 112.723000,
        "container_yard": "CY1"
      },
      {
        "id": "RTG03",
        "name": "RTG03 - CY1",
        "latitude": -7.205998,
        "longitude": 112.722836,
        "container_yard": "CY1"
      },
      {
        "id": "RTG04",
        "name": "RTG04 - CY1",
        "latitude": -7.206359,
        "longitude": 112.723258,
        "container_yard": "CY1"
      },
      {
        "id": "RTG05",
        "name": "RTG05 - CY1",
        "latitude": -7.206749,
        "longitude": 112.723464,
        "container_yard": "CY1"
      },
      {
        "id": "RTG06",
        "name": "RTG06 - CY1",
        "latitude": -7.207079,
        "longitude": 112.723899,
        "container_yard": "CY1"
      },
      {
        "id": "RTG07",
        "name": "RTG07 - CY2",
        "latitude": -7.208641,
        "longitude": 112.724410,
        "container_yard": "CY2"
      },
      {
        "id": "RTG08",
        "name": "RTG08 - CY2",
        "latitude": -7.208957,
        "longitude": 112.724877,
        "container_yard": "CY2"
      }
    ],
    "rs": [
      {
        "id": "RS",
        "name": "RS - CY3",
        "latitude": -7.207700,
        "longitude": 112.723028,
        "container_yard": "CY3"
      }
    ]
  },
  "special_locations": [
    {
      "id": "GATE",
      "name": "Gate In/Out",
      "latitude": -7.2099123,
      "longitude": 112.7244489
    },
    {
      "id": "PARKING",
      "name": "Parking",
      "latitude": -7.209907,
      "longitude": 112.724877
    }
  ],
  "summary": {
    "total_devices": 41,
    "towers": 26,
    "cctv": 4,
    "rtg": 8,
    "rs": 1,
    "special_locations": 2
  }
}
